app_root_template/qwstart.py
doc/conf.py
quickweb/__init__.py
quickweb/__main__.py
quickweb/_tempfile.py
quickweb/app.py
quickweb/app_manager.py
quickweb/colorhelper.py
quickweb/controller.py
quickweb/data_provider.py
quickweb/events.py
quickweb/http_unit_test.py
quickweb/modules.py
quickweb/startup.py
quickweb/template_manager.py
quickweb/test.py
quickweb/version.py
quickweb/doc/__init__.py
quickweb/features/__init__.py
quickweb/features/web/__init__.py
quickweb/features/web/content_directory.py
quickweb/features/web/controllers.py
quickweb/features/web/templates.py
quickweb/wsgi/__init__.py
test-app/boot/hello.py
test-app/lib/__init__.py
test-app/lib/test.py
test-app/tools/secureheaders.py
test-app/webroot/Test.py
test-app/webroot/TestComp.py
test-app/webroot/level2/Test.py
test-app/webroot/t1/index.py
quickweb-1.8.0.dist-info/LICENSE
quickweb-1.8.0.dist-info/METADATA
quickweb-1.8.0.dist-info/WHEEL
quickweb-1.8.0.dist-info/entry_points.txt
quickweb-1.8.0.dist-info/top_level.txt
quickweb-1.8.0.dist-info/RECORD
