Metadata-Version: 2.1
Name: quickweb
Version: 1.8.0
Summary: Rapid Development Python Web Framework
Home-page: https://github.com/joaompinto/quickweb
Author: João Pinto
Author-email: lamego.pinto@gmail.com
License: MIT
Platform: UNKNOWN
Requires-Dist: CherryPy
Requires-Dist: Jinja2
Requires-Dist: docopt (>=0.6.2)
Requires-Dist: Requests
Requires-Dist: pyyaml
Requires-Dist: colorama
Requires-Dist: termcolor
Requires-Dist: webtest
Requires-Dist: WSGIProxy2
Requires-Dist: markdown
